lemx/__init__.py
lemx/dictionary.csv
lemx/lemmatizer.py
lemx-0.2.1.dist-info/METADATA
lemx-0.2.1.dist-info/WHEEL
lemx-0.2.1.dist-info/top_level.txt
lemx-0.2.1.dist-info/RECORD
