Metadata-Version: 2.2
Name: LemX
Version: 0.2.1
Summary: A Banglish lemmatizer and word corrector using Levenshtein Distance Developped By Pronoy Kumar Mondal Under the supervision of Md. Sadekur Rahman & Sadman Sadik Khan.
Home-page: https://github.com/yourusername/LemX
Author: Pronoy Kumar Mondal
Author-email: pronoy15-14744@diu.edu.bd
Classifier: Programming Language :: Python :: 3
Classifier: License :: OSI Approved :: MIT License
Classifier: Operating System :: OS Independent
Requires-Python: >=3.6
Requires-Dist: python-Levenshtein
Dynamic: author
Dynamic: author-email
Dynamic: classifier
Dynamic: description
Dynamic: description-content-type
Dynamic: home-page
Dynamic: requires-dist
Dynamic: requires-python
Dynamic: summary
